LICENSE
README.md
pyproject.toml
setup.py
fastapi_entity_auth/__init__.py
fastapi_entity_auth/fastapi_entity_auth.py
fastapi_entity_auth.egg-info/PKG-INFO
fastapi_entity_auth.egg-info/SOURCES.txt
fastapi_entity_auth.egg-info/dependency_links.txt
fastapi_entity_auth.egg-info/requires.txt
fastapi_entity_auth.egg-info/top_level.txt