Metadata-Version: 2.1
Name: fastapi-entity-auth
Version: 0.0.1
Summary: A FastAPI extension that provides support for JWT authentication (secure, easy to use, and lightweight).
Home-page: https://github.com/gangstand/fastapi-entity-auth
Author: gangstand
Author-email: ganggstand@gmail.ru
License: License :: OSI Approved :: MIT License
Classifier: License :: OSI Approved :: MIT License
Classifier: Programming Language :: Python
Classifier: Programming Language :: Python :: 3.8
Classifier: Programming Language :: Python :: 3.9
Classifier: Programming Language :: Python :: 3.10
Classifier: Programming Language :: Python :: 3.11
Classifier: Programming Language :: Python :: 3.12
License-File: LICENSE
Requires-Dist: pyjwt
Requires-Dist: fastapi
Requires-Dist: cryptography
